rippler/__init__.py
rippler/main.py
rippler/test_main.py
rippler-1.0.0.dist-info/LICENSE.md
rippler-1.0.0.dist-info/METADATA
rippler-1.0.0.dist-info/WHEEL
rippler-1.0.0.dist-info/top_level.txt
rippler-1.0.0.dist-info/RECORD
