Metadata-Version: 2.1
Name: rippler
Version: 1.0.0
Summary: An interface to the Ripples drink printer platform
Author-email: Pierre-Nicolas Durette <pndurette@gmail.com>
License: MIT License        
Project-URL: homepage, https://github.com/pndurette/rippler
Project-URL: documentation, https://github.com/pndurette/rippler/blob/main/docs/README.md
Project-URL: repository, https://github.com/pndurette/rippler
Project-URL: changelog, https://github.com/pndurette/rippler/blob/main/CHANGELOG.md
Requires-Python: >=3.6
License-File: LICENSE.md
Requires-Dist: requests (~=2.28.0)
Provides-Extra: dev
Requires-Dist: pytest (~=7.1.3) ; extra == 'dev'
Provides-Extra: docs
Requires-Dist: GenDoc (~=1.0.1) ; extra == 'docs'
